tundra/Base_module.py
tundra/Databases_module.py
tundra/FileReader.py
tundra/Module_description.py
tundra/Permission_state.py
tundra/Reader.py
tundra/Roles_module.py
tundra/Spec_generator.py
tundra/Spesification.py
tundra/Spesification_description.py
tundra/Users_module.py
tundra/Warehouses_module.py
tundra/Writer_yaml_file.py
tundra/__init__.py
tundra/file_loader.py
tundra/loader_local_file.py
tundra/tundra.py
tundra/txt_generator.py
tundra/verification_module.py
tundra_permissions-0.1.0.dist-info/LICENSE
tundra_permissions-0.1.0.dist-info/METADATA
tundra_permissions-0.1.0.dist-info/WHEEL
tundra_permissions-0.1.0.dist-info/entry_points.txt
tundra_permissions-0.1.0.dist-info/top_level.txt
tundra_permissions-0.1.0.dist-info/RECORD
