Metadata-Version: 2.1
Name: tundra-permissions
Version: 0.1.0
Summary: Concatenates multiple Permifrost spec files into one
License:                     GNU GENERAL PUBLIC LICENSE
Requires-Python: >=3.12
License-File: LICENSE
Requires-Dist: click>=8.0.3
Requires-Dist: pyyaml>=6.0.2
Requires-Dist: regex>=2024.11.6
Requires-Dist: dictdiffer>=0.9.0
Requires-Dist: wheel>=0.45.1
